bed2seq/__init__.py
bed2seq/ascii.py
bed2seq/bed2seq.py
bed2seq/info.py
bed2seq/test.py
bed2seq-0.4.0.dist-info/licenses/LICENCE.md
bed2seq-0.4.0.dist-info/METADATA
bed2seq-0.4.0.dist-info/WHEEL
bed2seq-0.4.0.dist-info/entry_points.txt
bed2seq-0.4.0.dist-info/top_level.txt
bed2seq-0.4.0.dist-info/RECORD
