Metadata-Version: 2.4
Name: bed2seq
Version: 0.4.0
Summary: From a BED file, return the sequences according to the genome supplied
Home-page: https://github.com/bio2m/bed2seq
Author: Benoit Guibert
Author-email: benoit.guibert@free.fr
License: GPLv3
Classifier: Development Status :: 3 - Alpha
Classifier: License :: OSI Approved :: GNU General Public License v3 (GPLv3)
Classifier: Operating System :: POSIX :: Linux
Classifier: Natural Language :: English
Classifier: Intended Audience :: Science/Research
Requires-Python: >=3.7
License-File: LICENCE.md
Requires-Dist: pyfaidx
Dynamic: author
Dynamic: author-email
Dynamic: classifier
Dynamic: description
Dynamic: description-content-type
Dynamic: home-page
Dynamic: license
Dynamic: license-file
Dynamic: requires-dist
Dynamic: requires-python
Dynamic: summary
